django_smart_storages-0.1.0.dist-info/licenses/LICENSE
smart_storages/__init__.py
smart_storages/s3_backend.py
django_smart_storages-0.1.0.dist-info/METADATA
django_smart_storages-0.1.0.dist-info/WHEEL
django_smart_storages-0.1.0.dist-info/top_level.txt
django_smart_storages-0.1.0.dist-info/RECORD
